[
{
  "asin": "B0B7NTY2S6",
  "title": "SanDisk Extreme Carte SDXC 128 Go – V30 UHS-I, jusqu’à 180 Mo/s + logiciel RescuePRO Deluxe inclus",
  "brand": "SanDisk",
  "capacity_gb": 128,
  "interface": "UHS-I",
  "type": "Externe",
  "form_factor_protocol": "Carte Mémoire",
  "storage_type": "SD",
  "price_cents": 0,
  "rating": null,
  "reviews": 0,
  "url_affiliate": "https://www.amazon.fr/SanDisk-Extreme-RescuePRO-Deluxe-jusqu%C3%A0/dp/B0B7NTY2S6?th=1&linkCode=ll1&tag=addfr-21&linkId=cfd1c153b012997d0ca7b4579e5f4b30&language=fr_FR&ref_=as_li_ss_tl",
  "disk_type": "Carte Mémoire"
},
{
  "asin": "B09X7FXHVJ",
  "title": "SanDisk Extreme 128 Go SDXC UHS-I Memory Card – up to 180MB/s, V30, U3, 4K UHD, RescuePRO Deluxe Software",
  "brand": "SanDisk",
  "capacity_gb": 128,
  "interface": "UHS-I",
  "type": "Externe",
  "form_factor_protocol": "Carte Mémoire",
  "storage_type": "SD",
  "price_cents": 0,
  "rating": null,
  "reviews": 0,
  "url_affiliate": "https://www.amazon.fr/SanDisk-Cards-Extreme-128GB-Memory/dp/B09X7FXHVJ?tag=addfr-21",
  "disk_type": "Carte Mémoire"
},
{
  "asin": "B08XZ2KS1F",
  "title": "Lexar Carte microSDXC 128 Go avec adaptateur SD – UHS-I U3 V30 A2, jusqu’à 160 Mo/s, pour smartphone, tablette, drone, caméra d’action",
  "brand": "Lexar",
  "capacity_gb": 128,
  "interface": "UHS-I",
  "type": "Externe",
  "form_factor_protocol": "Carte Mémoire",
  "storage_type": "microSD",
  "price_cents": 0,
  "rating": null,
  "reviews": 0,
  "url_affiliate": "https://www.amazon.fr/Lexar-Carte-Micro-adaptateur-Smartphone/dp/B08XZ2KS1F?tag=addfr-21",
  "disk_type": "Carte Mémoire"
},
{
  "asin": "B0D6KKG2RK",
  "title": "Lot de 2 Carte Mémoire 128 Go avec Adaptateur, Carte Mémoire TF Haute Vitesse, UHS-I, A1, C10",
  "brand": "Bliksem",
  "capacity_gb": 128,
  "interface": "UHS-I",
  "type": "Externe",
  "form_factor_protocol": "Carte Mémoire",
  "storage_type": "microSD",
  "price_cents": 0,
  "rating": null,
  "reviews": 0,
  "url_affiliate": "https://www.amazon.fr/dp/B0D6KKG2RK?tag=addfr-21",
  "disk_type": "Carte Mémoire"
},
{
  "asin": "B0B7NV73PJ",
  "title": "SanDisk Carte microSDXC 128 Go avec adaptateur – jusqu'à 140 Mo/s, A1, U1, C10, homologuée pour Chromebook",
  "brand": "SanDisk",
  "capacity_gb": 128,
  "interface": "UHS-I",
  "type": "Externe",
  "form_factor_protocol": "Carte Mémoire",
  "storage_type": "microSD",
  "price_cents": 0,
  "rating": null,
  "reviews": 0,
  "url_affiliate": "https://www.amazon.fr/dp/B0B7NV73PJ?tag=addfr-21",
  "disk_type": "Carte Mémoire"
},
{
  "asin": "B0B7NVXLLM",
  "title": "SanDisk Carte microSDXC 256 Go avec adaptateur – jusqu'à 140 Mo/s, A1, U1, C10, homologuée pour Chromebook",
  "brand": "SanDisk",
  "capacity_gb": 256,
  "interface": "UHS-I",
  "type": "Externe",
  "form_factor_protocol": "Carte Mémoire",
  "storage_type": "microSD",
  "price_cents": 0,
  "rating": null,
  "reviews": 0,
  "url_affiliate": "https://www.amazon.fr/dp/B0B7NVXLLM?tag=addfr-21",
  "disk_type": "Carte Mémoire"
},
{
  "asin": "B09X7DNF6G",
  "title": "SanDisk Extreme microSDXC 128 Go + adaptateur SD – jusqu'à 190 Mo/s, A2, U3, V30, avec logiciel RescuePRO Deluxe",
  "brand": "SanDisk",
  "capacity_gb": 128,
  "interface": "UHS-I",
  "type": "Externe",
  "form_factor_protocol": "Carte Mémoire",
  "storage_type": "microSD",
  "price_cents": 0,
  "rating": null,
  "reviews": 0,
  "url_affiliate": "https://www.amazon.fr/dp/B09X7DNF6G?tag=addfr-21",
  "disk_type": "Carte Mémoire"
},
{
  "asin": "B08KSTYD3P",
  "title": "Patriot Memory EP Series Carte microSDXC 128 Go – UHS-I U3 A1 V30, jusqu’à 100 Mo/s en lecture",
  "brand": "Patriot Memory",
  "capacity_gb": 128,
  "interface": "UHS-I",
  "type": "Externe",
  "form_factor_protocol": "Carte Mémoire",
  "storage_type": "microSD",
  "price_cents": 0,
  "rating": null,
  "reviews": 0,
  "url_affiliate": "https://www.amazon.fr/dp/B08KSTYD3P?tag=addfr-21",
  "disk_type": "Carte Mémoire"
},
{
  "asin": "B09X7C7NCZ",
  "title": "SanDisk Extreme microSDXC 256 Go + adaptateur SD – jusqu'à 190 Mo/s, A2, U3, V30, avec logiciel RescuePRO Deluxe",
  "brand": "SanDisk",
  "capacity_gb": 256,
  "interface": "UHS-I",
  "type": "Externe",
  "form_factor_protocol": "Carte Mémoire",
  "storage_type": "microSD",
  "price_cents": 0,
  "rating": null,
  "reviews": 0,
  "url_affiliate": "https://www.amazon.fr/dp/B09X7C7NCZ?tag=addfr-21",
  "disk_type": "Carte Mémoire"
},
{
  "asin": "B07QD6R5L7",
  "title": "SanDisk microSDXC 128 Go pour Nintendo Switch – Produit sous licence officielle, jusqu'à 100 Mo/s",
  "brand": "SanDisk",
  "capacity_gb": 128,
  "interface": "UHS-I",
  "type": "Externe",
  "storage_type": "Gaming Console",
  "form_factor_protocol": "Carte Mémoire",
  "price_cents": 0,
  "rating": null,
  "reviews": 0,
  "url_affiliate": "https://www.amazon.fr/dp/B07QD6R5L7?tag=addfr-21",
  "disk_type": "Carte Mémoire"
},
{
  "asin": "B0B7NXBM6P",
  "title": "SanDisk Extreme microSDXC 64 Go + adaptateur SD – jusqu'à 170 Mo/s, A2, U3, V30, avec logiciel RescuePRO Deluxe",
  "brand": "SanDisk",
  "capacity_gb": 64,
  "interface": "UHS-I",
  "type": "Externe",
  "storage_type": "microSD",
  "form_factor_protocol": "Carte Mémoire",
  "price_cents": 0,
  "rating": null,
  "reviews": 0,
  "url_affiliate": "https://www.amazon.fr/dp/B0B7NXBM6P?tag=addfr-21",
  "disk_type": "Carte Mémoire"
},
{
  "asin": "B08GYG6T12",
  "title": "SanDisk Ultra microSDXC 128 Go + adaptateur SD – jusqu'à 120 Mo/s, Class 10, UHS-I, A1",
  "brand": "SanDisk",
  "capacity_gb": 128,
  "interface": "UHS-I",
  "type": "Externe",
  "storage_type": "microSD",
  "form_factor_protocol": "Carte Mémoire",
  "price_cents": 0,
  "rating": null,
  "reviews": 0,
  "url_affiliate": "https://www.amazon.fr/dp/B08GYG6T12?tag=addfr-21",
  "disk_type": "Carte Mémoire"
}
]
